sema/RSff.sv
/* WHAT IS THIS? 
// This module is a synchronous RS-flip-flop.                                                                                                                                                                                                                                                                                                                                                                                                                                                                                                                                                                 
*/


module RSff(
    input logic set,
    input logic reset,
    input logic clk,
    
    output logic out);

    always @(posedge clk) begin
        if(reset)
            out = 1'b0;
        else begin
            if(set)
                out = 1'b1;
            else
                out = out;
        end 
    end
endmodule

sema/DffPIPO_CE_SET.sv
/* WHAT IS THIS? 
// This module is an D-flip-flop. 
   It can be set to a given value in SET.
   It size/width can be set to the size given in SIZE                                                                                                                                                                                                                                                                                                                                                                                                                                                                                                                                                                                         
*/

module DffPIPO_CE_SET #(parameter SET = 0, parameter SIZE = 8)(
    input CE,
    input [SIZE-1:0] D,
    input clk,
    input nReset,

    output reg [SIZE-1:0] out
);

always @(posedge clk ) begin
    if(nReset) begin
        if(CE==1)
            out <= D;
    end
    else 
        out <= SET;
end
endmodule

sema/sem_mem_connector.sv
`include "DffPIPO_CE_SET.sv"
`include "RSff.sv"

module sem_mem_connector(
    input logic clk_s,
    input logic rstn_s,

    output logic sema_valid_i_s_B,
    output logic sema_data_i_s_B,
    input logic sema_ready_o_s_B,

    output logic sema_is_empty_i_s_A,
    input logic sema_write_o_s_A,
    input logic sema_data_o_s_A);

    wire wire_is_empty;

    DffPIPO_CE_SET #(.SIZE(1)) Dff1  (
        .CE(sema_write_o_s_A),
        .D(sema_data_o_s_A),
        .clk(clk_s),
        .nReset(rstn_s),

        .out(sema_data_i_s_B)
    );

    RSff RSff1(
        .set(sema_write_o_s_A),
        .reset(sema_ready_o_s_B & rstn_s),
        .clk(clk_s),
        .out(wire_is_empty)
    );

    assign sema_valid_i_s_B = wire_is_empty;
    assign sema_is_empty_i_s_A = ~wire_is_empty;
endmodule

sema/sema.sv
`include "sem_mem_connector.sv"

module sema(
  // Naming is inherited after CPU
  // The output/input should be INVERTED compared to the 'i'/'o' letters in the sema signals

 input logic clk_s,
 input logic rstn_s,

 input logic sema_write_o_s_A,
 input logic sema_data_o_s_A,
 output logic sema_is_empty_i_s_A,

 input logic sema_write_o_s_B,
 input logic sema_data_o_s_B,
 output logic sema_is_empty_i_s_B,

 output logic sema_data_i_s_A,
 output logic sema_valid_i_s_A,
 input logic sema_ready_o_s_A,

 output logic sema_data_i_s_B,
 output logic sema_valid_i_s_B,
 input logic sema_ready_o_s_B);


  logic wire_wr_A;
  logic wire_wr_B; 
  assign wire_wr_A = sema_write_o_s_A;
  assign wire_wr_B = ~sema_write_o_s_A & sema_write_o_s_B;

  sem_mem_connector connector_cpuA_2_cpuB( // Connector: A->B; Connection A->B
    .clk_s(clk_s),
    .rstn_s(rstn_s),
    .sema_write_o_s_A(wire_wr_A),
    .sema_data_o_s_A(sema_data_o_s_A),
    .sema_is_empty_i_s_A(sema_is_empty_i_s_A),
    .sema_valid_i_s_B(sema_valid_i_s_B),
    .sema_data_i_s_B(sema_data_i_s_B),
    .sema_ready_o_s_B(sema_ready_o_s_B)
  );

  sem_mem_connector connector_cpuB_2_cpuA( // Connector: A->B; Connection B->A
    .clk_s(clk_s),
    .rstn_s(rstn_s),
    .sema_write_o_s_A(wire_wr_B),
    .sema_data_o_s_A(sema_data_o_s_B),
    .sema_is_empty_i_s_A(sema_is_empty_i_s_B),
    .sema_valid_i_s_B(sema_valid_i_s_A),
    .sema_data_i_s_B(sema_data_i_s_A),
    .sema_ready_o_s_B(sema_ready_o_s_A)
  );

endmodule

sema/sema_tb.sv
/* WHAT IS THIS? 
 This is a Testbench that tests all modules
*/
`define tb_path "tb_files/sema_tb.vcd"
`define simulationTime #100

`timescale  1ns/1ps


`include "sema.sv"

module sema_tb;

logic tb_clk_s;
logic tb_rstn_s;

logic tb_sema_write_o_s_A;
logic tb_sema_data_o_s_A;
logic tb_sema_is_empty_i_s_A;

logic tb_sema_write_o_s_B;
logic tb_sema_data_o_s_B;
logic tb_sema_is_empty_i_s_B;

logic tb_sema_data_i_s_A;
logic tb_sema_valid_i_s_A;
logic tb_sema_ready_o_s_A;

logic tb_sema_data_i_s_B;
logic tb_sema_valid_i_s_B;
logic tb_sema_ready_o_s_B;


sema sema1(
.clk_s(tb_clk_s),
.rstn_s(tb_rstn_s),

.sema_write_o_s_A(tb_sema_write_o_s_A),         //INPUT   write_AB
.sema_data_o_s_A(tb_sema_data_o_s_A),           //INPUT   write_AB
.sema_is_empty_i_s_A(tb_sema_is_empty_i_s_A),   //output  write_AB

.sema_data_i_s_B(tb_sema_data_i_s_B),           //output  write_AB
.sema_valid_i_s_B(tb_sema_valid_i_s_B),         //output  write_AB
.sema_ready_o_s_B(tb_sema_ready_o_s_B),         //INPUT   write_AB


.sema_write_o_s_B(tb_sema_write_o_s_B),         //INPUT   write_BA
.sema_data_o_s_B(tb_sema_data_o_s_B),           //INPUT   write_BA
.sema_is_empty_i_s_B(tb_sema_is_empty_i_s_B),   //output  write_BA

.sema_data_i_s_A(tb_sema_data_i_s_A),           //output  write_BA
.sema_valid_i_s_A(tb_sema_valid_i_s_A),         //output  write_BA
.sema_ready_o_s_A(tb_sema_ready_o_s_A)         //INPUT   write_BA
);

//============================================================================
//******************************* STATE MACHINE ******************************
//============================================================================

parameter st_AB_0 = 0;
parameter st_AB_1 = 1;
parameter st_AB_2 = 2;
parameter st_AB_3 = 3;
parameter st_AB_4 = 4;
parameter st_AB_5 = 5;
parameter st_AB_6 = 6;

integer state = 100;
reg data = 1'b1;
// We operate on 3 inputs to affect 3 outputs (6 signals)

always @(posedge tb_clk_s)
case(state) 
    st_AB_0: begin
        tb_sema_data_o_s_A = data;
        state <= st_AB_1;
    end
    st_AB_1: begin
        tb_sema_write_o_s_A = 1'b1;
        state <= st_AB_2;
    end
    st_AB_2: begin
        
        state <= st_AB_3;
    end
    st_AB_3: begin
        tb_sema_write_o_s_A = 1'b0;
        tb_sema_ready_o_s_B = 1'b1;
        state <= st_AB_4;
    end
    st_AB_4: begin

        state <= st_AB_5;
    end
    st_AB_5: begin
        tb_sema_ready_o_s_B = 1'b0;
        state <= st_AB_0;
        data=~data;
    end

    default begin
        tb_sema_write_o_s_A = 1'bx;
        tb_sema_ready_o_s_B = 1'bx;
        tb_sema_data_o_s_A  = 1'bx;
    end
endcase

//============================================================================
//******************************** SIMULATION ********************************
//============================================================================

initial begin

    #20 state = 0;
end











//============================================================================
//***************************** SIMULATION BASICS ****************************
//============================================================================


initial begin //clk
forever begin
    #5 tb_clk_s = ~tb_clk_s;
end
end

initial begin // start values
tb_clk_s = 0;
tb_rstn_s = 0;
#6 tb_rstn_s = 1;

//`simulationTime $finish;
 #200 $finish;
end

initial begin // file save
   
    $dumpfile(`tb_path);
    $dumpvars;
    $dumpon;
end


endmodule

sema/tb_files/sema_tb.vcd
$date
	Thu Jan 23 14:48:39 2025
$end
$version
	Icarus Verilog
$end
$timescale
	1ps
$end
$scope module sema_tb $end
$var wire 1 ! tb_sema_valid_i_s_B $end
$var wire 1 " tb_sema_valid_i_s_A $end
$var wire 1 # tb_sema_is_empty_i_s_B $end
$var wire 1 $ tb_sema_is_empty_i_s_A $end
$var wire 1 % tb_sema_data_i_s_B $end
$var wire 1 & tb_sema_data_i_s_A $end
$var parameter 32 ' st_AB_0 $end
$var parameter 32 ( st_AB_1 $end
$var parameter 32 ) st_AB_2 $end
$var parameter 32 * st_AB_3 $end
$var parameter 32 + st_AB_4 $end
$var parameter 32 , st_AB_5 $end
$var parameter 32 - st_AB_6 $end
$var reg 1 . data $end
$var reg 1 / tb_clk_s $end
$var reg 1 0 tb_rstn_s $end
$var reg 1 1 tb_sema_data_o_s_A $end
$var reg 1 2 tb_sema_data_o_s_B $end
$var reg 1 3 tb_sema_ready_o_s_A $end
$var reg 1 4 tb_sema_ready_o_s_B $end
$var reg 1 5 tb_sema_write_o_s_A $end
$var reg 1 6 tb_sema_write_o_s_B $end
$var integer 32 7 state [31:0] $end
$scope module sema1 $end
$var wire 1 / clk_s $end
$var wire 1 0 rstn_s $end
$var wire 1 1 sema_data_o_s_A $end
$var wire 1 2 sema_data_o_s_B $end
$var wire 1 3 sema_ready_o_s_A $end
$var wire 1 4 sema_ready_o_s_B $end
$var wire 1 5 sema_write_o_s_A $end
$var wire 1 6 sema_write_o_s_B $end
$var wire 1 8 wire_wr_A $end
$var wire 1 9 wire_wr_B $end
$var wire 1 ! sema_valid_i_s_B $end
$var wire 1 " sema_valid_i_s_A $end
$var wire 1 # sema_is_empty_i_s_B $end
$var wire 1 $ sema_is_empty_i_s_A $end
$var wire 1 % sema_data_i_s_B $end
$var wire 1 & sema_data_i_s_A $end
$scope module connector_cpuA_2_cpuB $end
$var wire 1 / clk_s $end
$var wire 1 0 rstn_s $end
$var wire 1 1 sema_data_o_s_A $end
$var wire 1 $ sema_is_empty_i_s_A $end
$var wire 1 4 sema_ready_o_s_B $end
$var wire 1 ! sema_valid_i_s_B $end
$var wire 1 8 sema_write_o_s_A $end
$var wire 1 : wire_is_empty $end
$var wire 1 % sema_data_i_s_B $end
$scope module Dff1 $end
$var wire 1 8 CE $end
$var wire 1 1 D $end
$var wire 1 / clk $end
$var wire 1 0 nReset $end
$var parameter 32 ; SET $end
$var parameter 32 < SIZE $end
$var reg 1 % out $end
$upscope $end
$scope module RSff1 $end
$var wire 1 / clk $end
$var wire 1 = reset $end
$var wire 1 8 set $end
$var reg 1 : out $end
$upscope $end
$upscope $end
$scope module connector_cpuB_2_cpuA $end
$var wire 1 / clk_s $end
$var wire 1 0 rstn_s $end
$var wire 1 2 sema_data_o_s_A $end
$var wire 1 # sema_is_empty_i_s_A $end
$var wire 1 3 sema_ready_o_s_B $end
$var wire 1 " sema_valid_i_s_B $end
$var wire 1 9 sema_write_o_s_A $end
$var wire 1 > wire_is_empty $end
$var wire 1 & sema_data_i_s_B $end
$scope module Dff1 $end
$var wire 1 9 CE $end
$var wire 1 2 D $end
$var wire 1 / clk $end
$var wire 1 0 nReset $end
$var parameter 32 ? SET $end
$var parameter 32 @ SIZE $end
$var reg 1 & out $end
$upscope $end
$scope module RSff1 $end
$var wire 1 / clk $end
$var wire 1 A reset $end
$var wire 1 9 set $end
$var reg 1 > out $end
$upscope $end
$upscope $end
$upscope $end
$upscope $end
$enddefinitions $end
$comment Show the parameter values. $end
$dumpall
b1 @
b0 ?
b1 <
b0 ;
b110 -
b101 ,
b100 +
b11 *
b10 )
b1 (
b0 '
$end
#0
$dumpvars
0A
x>
0=
x:
x9
x8
b1100100 7
x6
x5
x4
x3
x2
x1
00
0/
1.
x&
x%
x$
x#
x"
x!
$end
#5000
0%
0&
1/
#6000
x=
xA
10
#10000
0/
#15000
1/
#20000
0/
b0 7
#25000
b1 7
11
1/
#30000
0/
#35000
b10 7
09
18
15
1/
#40000
0/
#45000
1%
b11 7
0$
1!
1:
1/
#50000
0/
#55000
b100 7
x9
1=
14
08
05
1/
#60000
0/
#65000
b101 7
1$
0!
0:
1/
#70000
0/
#75000
b0 7
0=
0.
04
1/
#80000
0/
#85000
b1 7
01
1/
#90000
0/
#95000
b10 7
09
18
15
1/
#100000
0/
#105000
0%
b11 7
0$
1!
1:
1/
#110000
0/
#115000
b100 7
x9
1=
14
08
05
1/
#120000
0/
#125000
b101 7
1$
0!
0:
1/
#130000
0/
#135000
b0 7
0=
1.
04
1/
#140000
0/
#145000
b1 7
11
1/
#150000
0/
#155000
b10 7
09
18
15
1/
#160000
0/
#165000
1%
b11 7
0$
1!
1:
1/
#170000
0/
#175000
b100 7
x9
1=
14
08
05
1/
#180000
0/
#185000
b101 7
1$
0!
0:
1/
#190000
0/
#195000
b0 7
0=
0.
04
1/
#200000
0/
#205000
b1 7
01
1/
